odoo/addons/account_reporting_net_weight/README.rst
odoo/addons/account_reporting_net_weight/__init__.py
odoo/addons/account_reporting_net_weight/__manifest__.py
odoo/addons/account_reporting_net_weight/i18n/account_reporting_net_weight.pot
odoo/addons/account_reporting_net_weight/i18n/ca.po
odoo/addons/account_reporting_net_weight/i18n/es.po
odoo/addons/account_reporting_net_weight/readme/CONFIGURE.rst
odoo/addons/account_reporting_net_weight/readme/CONTRIBUTORS.rst
odoo/addons/account_reporting_net_weight/readme/DESCRIPTION.rst
odoo/addons/account_reporting_net_weight/readme/USAGE.rst
odoo/addons/account_reporting_net_weight/reports/__init__.py
odoo/addons/account_reporting_net_weight/reports/account_invoice_report.py
odoo/addons/account_reporting_net_weight/static/description/icon.png
odoo/addons/account_reporting_net_weight/static/description/index.html
odoo12_addon_account_reporting_net_weight-12.0.1.0.0.99.dev3.dist-info/METADATA
odoo12_addon_account_reporting_net_weight-12.0.1.0.0.99.dev3.dist-info/WHEEL
odoo12_addon_account_reporting_net_weight-12.0.1.0.0.99.dev3.dist-info/top_level.txt
odoo12_addon_account_reporting_net_weight-12.0.1.0.0.99.dev3.dist-info/RECORD
